optiline/__init__.py
optiline-0.0.1.dist-info/LICENSE
optiline-0.0.1.dist-info/METADATA
optiline-0.0.1.dist-info/WHEEL
optiline-0.0.1.dist-info/top_level.txt
optiline-0.0.1.dist-info/RECORD
