Metadata-Version: 2.1
Name: optiline
Version: 0.0.1
Summary: Repository focused on the implementation and resolution of optimization methods in Python.
Author: aciriano
License: MIT License
Project-URL: repository, https://github.com/aciriano/OptiLine
Classifier: Programming Language :: Python :: 3
Classifier: Programming Language :: Python :: 3.9
Classifier: Programming Language :: Python :: 3.10
Classifier: License :: OSI Approved :: MIT License
Classifier: Operating System :: OS Independent
Requires-Python: >=3.9
License-File: LICENSE
Provides-Extra: dev
Requires-Dist: ruff ; extra == 'dev'
Requires-Dist: pytest ; extra == 'dev'
Requires-Dist: pre-commit ; extra == 'dev'
Requires-Dist: pytest-cov ; extra == 'dev'
Requires-Dist: tox ; extra == 'dev'
Requires-Dist: reorder-python-imports ; extra == 'dev'
Requires-Dist: mypy ; extra == 'dev'
